data_sc_it19/__init__.py
data_sc_it19/WEEK_2_std/__init__.py
data_sc_it19/WEEK_2_std/numpy_tasks.py
data_sc_it19/WEEK_2_std/numpy_tasks_1.py
data_sc_it19/WEEK_3/__init__.py
data_sc_it19/WEEK_3/html_pandas.py
data_sc_it19/WEEK_3/merging_series.py
data_sc_it19/WEEK_3/pandas_exercises_2.py
data_sc_it19/WEEK_3_std/Pandas_Dataframe_jup.py
data_sc_it19/WEEK_3_std/__init__.py
data_sc_it19/WEEK_4/Matplotlib_jpt.py
data_sc_it19/WEEK_4/__init__.py
data_sc_it19/WEEK_4_std/__init__.py
data_sc_it19/WEEK_4_std/bar_plot_jtp.py
data_sc_it19/WEEK_4_std/box_plot_jtp.py
data_sc_it19/WEEK_4_std/scatter_heat_jpt.py
data_sc_it19-0.0.5.dist-info/METADATA
data_sc_it19-0.0.5.dist-info/WHEEL
data_sc_it19-0.0.5.dist-info/top_level.txt
data_sc_it19-0.0.5.dist-info/RECORD
