Metadata-Version: 2.1
Name: data-sc-it19
Version: 0.0.5
Summary: UNKNOWN
Home-page: UNKNOWN
Author: unknown
Author-email: UNKNOWN
License: UNKNOWN
Keywords: data
Platform: UNKNOWN
Classifier: Development Status :: 1 - Planning
Classifier: Intended Audience :: Developers
Classifier: Programming Language :: Python :: 3
Classifier: Operating System :: Unix
Classifier: Operating System :: MacOS :: MacOS X
Classifier: Operating System :: Microsoft :: Windows
Requires-Dist: numpy
Requires-Dist: matplotlib
Requires-Dist: pandas
